[
    {
        "key": "group_5fe136c3df088",
        "title": "Module Styles",
        "fields": [
            {
                "key": "field_5fe136d3cfab6",
                "label": "Slider Styles",
                "name": "module_styles_slider",
                "type": "repeater",
                "instructions": "",
                "required": 0,
                "conditional_logic": 0,
                "wrapper": {
                    "width": "",
                    "class": "",
                    "id": ""
                },
                "collapsed": "",
                "min": 0,
                "max": 0,
                "layout": "row",
                "button_label": "",
                "sub_fields": [
                    {
                        "key": "field_5fe139038300c",
                        "label": "Style Name",
                        "name": "style_name",
                        "type": "text",
                        "instructions": "",
                        "required": 0,
                        "conditional_logic": 0,
                        "wrapper": {
                            "width": "",
                            "class": "",
                            "id": ""
                        },
                        "default_value": "",
                        "placeholder": "",
                        "prepend": "",
                        "append": "",
                        "maxlength": ""
                    },
                    {
                        "key": "field_5fe136edcfab7",
                        "label": "Fields",
                        "name": "fields",
                        "type": "repeater",
                        "instructions": "",
                        "required": 0,
                        "conditional_logic": 0,
                        "wrapper": {
                            "width": "",
                            "class": "",
                            "id": ""
                        },
                        "collapsed": "",
                        "min": 0,
                        "max": 0,
                        "layout": "table",
                        "button_label": "",
                        "sub_fields": [
                            {
                                "key": "field_5fe138bf3df6e",
                                "label": "Name",
                                "name": "name",
                                "type": "text",
                                "instructions": "",
                                "required": 0,
                                "conditional_logic": 0,
                                "wrapper": {
                                    "width": "",
                                    "class": "",
                                    "id": ""
                                },
                                "default_value": "",
                                "placeholder": "",
                                "prepend": "",
                                "append": "",
                                "maxlength": ""
                            },
                            {
                                "key": "field_5fe138c43df6f",
                                "label": "Value",
                                "name": "value",
                                "type": "text",
                                "instructions": "",
                                "required": 0,
                                "conditional_logic": 0,
                                "wrapper": {
                                    "width": "",
                                    "class": "",
                                    "id": ""
                                },
                                "default_value": "",
                                "placeholder": "",
                                "prepend": "",
                                "append": "",
                                "maxlength": ""
                            }
                        ]
                    }
                ]
            },
            {
                "key": "field_5fe15d2393b88",
                "label": "Custom Styles",
                "name": "module_styles_custom",
                "type": "repeater",
                "instructions": "",
                "required": 0,
                "conditional_logic": 0,
                "wrapper": {
                    "width": "",
                    "class": "",
                    "id": ""
                },
                "collapsed": "",
                "min": 0,
                "max": 0,
                "layout": "row",
                "button_label": "",
                "sub_fields": [
                    {
                        "key": "field_5fe15d2393b89",
                        "label": "Style Name",
                        "name": "style_name",
                        "type": "text",
                        "instructions": "",
                        "required": 0,
                        "conditional_logic": 0,
                        "wrapper": {
                            "width": "",
                            "class": "",
                            "id": ""
                        },
                        "default_value": "",
                        "placeholder": "",
                        "prepend": "",
                        "append": "",
                        "maxlength": ""
                    },
                    {
                        "key": "field_5fe15d2393b8a",
                        "label": "Fields",
                        "name": "fields",
                        "type": "repeater",
                        "instructions": "",
                        "required": 0,
                        "conditional_logic": 0,
                        "wrapper": {
                            "width": "",
                            "class": "",
                            "id": ""
                        },
                        "collapsed": "",
                        "min": 0,
                        "max": 0,
                        "layout": "table",
                        "button_label": "",
                        "sub_fields": [
                            {
                                "key": "field_5fe15d2393b8b",
                                "label": "Name",
                                "name": "name",
                                "type": "text",
                                "instructions": "",
                                "required": 0,
                                "conditional_logic": 0,
                                "wrapper": {
                                    "width": "",
                                    "class": "",
                                    "id": ""
                                },
                                "default_value": "",
                                "placeholder": "",
                                "prepend": "",
                                "append": "",
                                "maxlength": ""
                            },
                            {
                                "key": "field_5fe15d2393b8c",
                                "label": "Value",
                                "name": "value",
                                "type": "text",
                                "instructions": "",
                                "required": 0,
                                "conditional_logic": 0,
                                "wrapper": {
                                    "width": "",
                                    "class": "",
                                    "id": ""
                                },
                                "default_value": "",
                                "placeholder": "",
                                "prepend": "",
                                "append": "",
                                "maxlength": ""
                            }
                        ]
                    }
                ]
            },
            {
                "key": "field_5fe183e93de98",
                "label": "Blurb Styles",
                "name": "module_styles_blurb",
                "type": "repeater",
                "instructions": "",
                "required": 0,
                "conditional_logic": 0,
                "wrapper": {
                    "width": "",
                    "class": "",
                    "id": ""
                },
                "collapsed": "",
                "min": 0,
                "max": 0,
                "layout": "row",
                "button_label": "",
                "sub_fields": [
                    {
                        "key": "field_5fe183e93de99",
                        "label": "Style Name",
                        "name": "style_name",
                        "type": "text",
                        "instructions": "",
                        "required": 0,
                        "conditional_logic": 0,
                        "wrapper": {
                            "width": "",
                            "class": "",
                            "id": ""
                        },
                        "default_value": "",
                        "placeholder": "",
                        "prepend": "",
                        "append": "",
                        "maxlength": ""
                    },
                    {
                        "key": "field_5fe183e93de9a",
                        "label": "Fields",
                        "name": "fields",
                        "type": "repeater",
                        "instructions": "",
                        "required": 0,
                        "conditional_logic": 0,
                        "wrapper": {
                            "width": "",
                            "class": "",
                            "id": ""
                        },
                        "collapsed": "",
                        "min": 0,
                        "max": 0,
                        "layout": "table",
                        "button_label": "",
                        "sub_fields": [
                            {
                                "key": "field_5fe183e93de9b",
                                "label": "Name",
                                "name": "name",
                                "type": "text",
                                "instructions": "",
                                "required": 0,
                                "conditional_logic": 0,
                                "wrapper": {
                                    "width": "",
                                    "class": "",
                                    "id": ""
                                },
                                "default_value": "",
                                "placeholder": "",
                                "prepend": "",
                                "append": "",
                                "maxlength": ""
                            },
                            {
                                "key": "field_5fe183e93de9c",
                                "label": "Value",
                                "name": "value",
                                "type": "text",
                                "instructions": "",
                                "required": 0,
                                "conditional_logic": 0,
                                "wrapper": {
                                    "width": "",
                                    "class": "",
                                    "id": ""
                                },
                                "default_value": "",
                                "placeholder": "",
                                "prepend": "",
                                "append": "",
                                "maxlength": ""
                            }
                        ]
                    }
                ]
            },
            {
                "key": "field_5ffcfcf093435",
                "label": "Text Styles",
                "name": "module_styles_text",
                "type": "repeater",
                "instructions": "",
                "required": 0,
                "conditional_logic": 0,
                "wrapper": {
                    "width": "",
                    "class": "",
                    "id": ""
                },
                "collapsed": "",
                "min": 0,
                "max": 0,
                "layout": "row",
                "button_label": "",
                "sub_fields": [
                    {
                        "key": "field_5ffcfcf093436",
                        "label": "Style Name",
                        "name": "style_name",
                        "type": "text",
                        "instructions": "",
                        "required": 0,
                        "conditional_logic": 0,
                        "wrapper": {
                            "width": "",
                            "class": "",
                            "id": ""
                        },
                        "default_value": "",
                        "placeholder": "",
                        "prepend": "",
                        "append": "",
                        "maxlength": ""
                    },
                    {
                        "key": "field_5ffcfcf093437",
                        "label": "Fields",
                        "name": "fields",
                        "type": "repeater",
                        "instructions": "",
                        "required": 0,
                        "conditional_logic": 0,
                        "wrapper": {
                            "width": "",
                            "class": "",
                            "id": ""
                        },
                        "collapsed": "",
                        "min": 0,
                        "max": 0,
                        "layout": "table",
                        "button_label": "",
                        "sub_fields": [
                            {
                                "key": "field_5ffcfcf093438",
                                "label": "Name",
                                "name": "name",
                                "type": "text",
                                "instructions": "",
                                "required": 0,
                                "conditional_logic": 0,
                                "wrapper": {
                                    "width": "",
                                    "class": "",
                                    "id": ""
                                },
                                "default_value": "",
                                "placeholder": "",
                                "prepend": "",
                                "append": "",
                                "maxlength": ""
                            },
                            {
                                "key": "field_5ffcfcf093439",
                                "label": "Value",
                                "name": "value",
                                "type": "text",
                                "instructions": "",
                                "required": 0,
                                "conditional_logic": 0,
                                "wrapper": {
                                    "width": "",
                                    "class": "",
                                    "id": ""
                                },
                                "default_value": "",
                                "placeholder": "",
                                "prepend": "",
                                "append": "",
                                "maxlength": ""
                            }
                        ]
                    }
                ]
            },
            {
                "key": "field_5ffcfd8b6f426",
                "label": "Heading Styles",
                "name": "module_styles_heading",
                "type": "repeater",
                "instructions": "",
                "required": 0,
                "conditional_logic": 0,
                "wrapper": {
                    "width": "",
                    "class": "",
                    "id": ""
                },
                "collapsed": "",
                "min": 0,
                "max": 0,
                "layout": "row",
                "button_label": "",
                "sub_fields": [
                    {
                        "key": "field_5ffcfd8b6f427",
                        "label": "Style Name",
                        "name": "style_name",
                        "type": "text",
                        "instructions": "",
                        "required": 0,
                        "conditional_logic": 0,
                        "wrapper": {
                            "width": "",
                            "class": "",
                            "id": ""
                        },
                        "default_value": "",
                        "placeholder": "",
                        "prepend": "",
                        "append": "",
                        "maxlength": ""
                    },
                    {
                        "key": "field_5ffcfd8b6f428",
                        "label": "Fields",
                        "name": "fields",
                        "type": "repeater",
                        "instructions": "",
                        "required": 0,
                        "conditional_logic": 0,
                        "wrapper": {
                            "width": "",
                            "class": "",
                            "id": ""
                        },
                        "collapsed": "",
                        "min": 0,
                        "max": 0,
                        "layout": "table",
                        "button_label": "",
                        "sub_fields": [
                            {
                                "key": "field_5ffcfd8b6f429",
                                "label": "Name",
                                "name": "name",
                                "type": "text",
                                "instructions": "",
                                "required": 0,
                                "conditional_logic": 0,
                                "wrapper": {
                                    "width": "",
                                    "class": "",
                                    "id": ""
                                },
                                "default_value": "",
                                "placeholder": "",
                                "prepend": "",
                                "append": "",
                                "maxlength": ""
                            },
                            {
                                "key": "field_5ffcfd8b6f42a",
                                "label": "Value",
                                "name": "value",
                                "type": "text",
                                "instructions": "",
                                "required": 0,
                                "conditional_logic": 0,
                                "wrapper": {
                                    "width": "",
                                    "class": "",
                                    "id": ""
                                },
                                "default_value": "",
                                "placeholder": "",
                                "prepend": "",
                                "append": "",
                                "maxlength": ""
                            }
                        ]
                    }
                ]
            },
            {
                "key": "field_5ffd152b744c1",
                "label": "Section Styles",
                "name": "module_styles_section",
                "type": "repeater",
                "instructions": "",
                "required": 0,
                "conditional_logic": 0,
                "wrapper": {
                    "width": "",
                    "class": "",
                    "id": ""
                },
                "collapsed": "",
                "min": 0,
                "max": 0,
                "layout": "row",
                "button_label": "",
                "sub_fields": [
                    {
                        "key": "field_5ffd152b744c2",
                        "label": "Style Name",
                        "name": "style_name",
                        "type": "text",
                        "instructions": "",
                        "required": 0,
                        "conditional_logic": 0,
                        "wrapper": {
                            "width": "",
                            "class": "",
                            "id": ""
                        },
                        "default_value": "",
                        "placeholder": "",
                        "prepend": "",
                        "append": "",
                        "maxlength": ""
                    },
                    {
                        "key": "field_5ffd152b744c3",
                        "label": "Fields",
                        "name": "fields",
                        "type": "repeater",
                        "instructions": "",
                        "required": 0,
                        "conditional_logic": 0,
                        "wrapper": {
                            "width": "",
                            "class": "",
                            "id": ""
                        },
                        "collapsed": "",
                        "min": 0,
                        "max": 0,
                        "layout": "table",
                        "button_label": "",
                        "sub_fields": [
                            {
                                "key": "field_5ffd152b744c4",
                                "label": "Name",
                                "name": "name",
                                "type": "text",
                                "instructions": "",
                                "required": 0,
                                "conditional_logic": 0,
                                "wrapper": {
                                    "width": "",
                                    "class": "",
                                    "id": ""
                                },
                                "default_value": "",
                                "placeholder": "",
                                "prepend": "",
                                "append": "",
                                "maxlength": ""
                            },
                            {
                                "key": "field_5ffd152b744c5",
                                "label": "Value",
                                "name": "value",
                                "type": "text",
                                "instructions": "",
                                "required": 0,
                                "conditional_logic": 0,
                                "wrapper": {
                                    "width": "",
                                    "class": "",
                                    "id": ""
                                },
                                "default_value": "",
                                "placeholder": "",
                                "prepend": "",
                                "append": "",
                                "maxlength": ""
                            }
                        ]
                    }
                ]
            }
        ],
        "location": [
            [
                {
                    "param": "options_page",
                    "operator": "==",
                    "value": "bmcb-settings"
                }
            ]
        ],
        "menu_order": 0,
        "position": "normal",
        "style": "default",
        "label_placement": "top",
        "instruction_placement": "label",
        "hide_on_screen": "",
        "active": true,
        "description": ""
    }
]